intel_gradio_theme/__init__.py
intel_gradio_theme/spark.css
intel_gradio_theme/spark_classic_blue.py
intel_gradio_theme/spark_tb.py
intel_gradio_theme-1.0.0.dist-info/licenses/LICENSE.md
intel_gradio_theme-1.0.0.dist-info/METADATA
intel_gradio_theme-1.0.0.dist-info/WHEEL
intel_gradio_theme-1.0.0.dist-info/top_level.txt
intel_gradio_theme-1.0.0.dist-info/RECORD
