Metadata-Version: 2.4
Name: intel_gradio_theme
Version: 1.0.0
Summary: A custom theme for Gradio
Home-page: https://github.com/intel/intel-gradio-theme
Author: Erin Olmon
Author-email: erin.olmon@intel.com
Maintainer: Erin Olmon, Agustín Francesa
Maintainer-email: erin.olmon@intel.com, agustin.francesa.alfaro@intel.com
License: Apache 2.0
Classifier: Programming Language :: Python :: 3
Classifier: License :: Other/Proprietary License
Classifier: Operating System :: OS Independent
Requires-Python: >=3.7
License-File: LICENSE.md
Requires-Dist: gradio>=4.0.0
Dynamic: author
Dynamic: author-email
Dynamic: classifier
Dynamic: description
Dynamic: description-content-type
Dynamic: home-page
Dynamic: license
Dynamic: license-file
Dynamic: maintainer
Dynamic: maintainer-email
Dynamic: requires-dist
Dynamic: requires-python
Dynamic: summary
